chat_portal/__init__.py
chat_portal/_database.py
chat_portal/_entities.py
chat_portal/_logger.py
chat_portal/_models.py
chat_portal/_portal.py
chat_portal/interface.py
chat_portal/platforms/__init__.py
chat_portal/platforms/_instagram.py
chat_portal/portals/__init__.py
chat_portal/portals/_gpt_portal.py
chat_portal-0.2.8.dist-info/LICENSE
chat_portal-0.2.8.dist-info/METADATA
chat_portal-0.2.8.dist-info/WHEEL
chat_portal-0.2.8.dist-info/RECORD
