Metadata-Version: 2.1
Name: chat-portal
Version: 0.2.8
Summary: Pair a profile's message contacts and transport modified messages that pretend to come from the initial profile
Home-page: https://github.com/kuco23/chat-portal/
License: MIT
Author: kuco23
Author-email: nseverkar@gmail.com
Requires-Python: >=3.10,<4.0
Classifier: License :: OSI Approved :: MIT License
Classifier: Programming Language :: Python :: 3
Classifier: Programming Language :: Python :: 3.10
Classifier: Programming Language :: Python :: 3.11
Classifier: Programming Language :: Python :: 3.12
Requires-Dist: SQLAlchemy (==2.0.23)
Requires-Dist: SQLAlchemy-Utils (==0.41.1)
Requires-Dist: openai (==1.6.1)
Requires-Dist: python-dotenv (==1.0.0)
Project-URL: Repository, https://github.com/kuco23/chat-portal/
